[
    {
        "key": "fr",
        "value": "0UVYlRcXNyjD7bOKV.AWeHnkWQ_At75QmYpYondaqiaOGTQWDbWQ3E2sdfZCJvEUptdJo.BoWW0t..AAA.0.0.BofKiG.AWf6UdBVoYp7_Rb6L0Y81rlSBaA",
        "domain": "facebook.com",
        "path": "/",
        "hostOnly": true,
        "creation": "2025-07-20T08:28:01.085Z",
        "lastAccessed": "2025-07-20T08:28:01.085Z"
    },
    {
        "key": "ps_l",
        "value": "1",
        "domain": "facebook.com",
        "path": "/",
        "hostOnly": true,
        "creation": "2025-07-20T08:28:01.085Z",
        "lastAccessed": "2025-07-20T08:28:01.085Z"
    },
    {
        "key": "ps_n",
        "value": "1",
        "domain": "facebook.com",
        "path": "/",
        "hostOnly": true,
        "creation": "2025-07-20T08:28:01.085Z",
        "lastAccessed": "2025-07-20T08:28:01.085Z"
    },
    {
        "key": "sb",
        "value": "LW1ZaGCpeDI-XqHwxT7XbdnI",
        "domain": "facebook.com",
        "path": "/",
        "hostOnly": true,
        "creation": "2025-07-20T08:28:01.085Z",
        "lastAccessed": "2025-07-20T08:28:01.085Z"
    },
    {
        "key": "datr",
        "value": "Lm1ZaAVCtiac7WJtN4rP35Lw",
        "domain": "facebook.com",
        "path": "/",
        "hostOnly": true,
        "creation": "2025-07-20T08:28:01.085Z",
        "lastAccessed": "2025-07-20T08:28:01.085Z"
    },
    {
        "key": "wl_cbv",
        "value": "v2%3Bclient_version%3A2875%3Btimestamp%3A1753000070",
        "domain": "facebook.com",
        "path": "/",
        "hostOnly": true,
        "creation": "2025-07-20T08:28:01.085Z",
        "lastAccessed": "2025-07-20T08:28:01.085Z"
    },
    {
        "key": "vpd",
        "value": "v1%3B634x375x3",
        "domain": "facebook.com",
        "path": "/",
        "hostOnly": true,
        "creation": "2025-07-20T08:28:01.085Z",
        "lastAccessed": "2025-07-20T08:28:01.085Z"
    },
    {
        "key": "pas",
        "value": "61560916929379%3A9pAjQxj8RA",
        "domain": "facebook.com",
        "path": "/",
        "hostOnly": true,
        "creation": "2025-07-20T08:28:01.085Z",
        "lastAccessed": "2025-07-20T08:28:01.085Z"
    },
    {
        "key": "locale",
        "value": "en_US",
        "domain": "facebook.com",
        "path": "/",
        "hostOnly": true,
        "creation": "2025-07-20T08:28:01.085Z",
        "lastAccessed": "2025-07-20T08:28:01.085Z"
    },
    {
        "key": "m_pixel_ratio",
        "value": "3",
        "domain": "facebook.com",
        "path": "/",
        "hostOnly": true,
        "creation": "2025-07-20T08:28:01.085Z",
        "lastAccessed": "2025-07-20T08:28:01.085Z"
    },
    {
        "key": "wd",
        "value": "375x812",
        "domain": "facebook.com",
        "path": "/",
        "hostOnly": true,
        "creation": "2025-07-20T08:28:01.085Z",
        "lastAccessed": "2025-07-20T08:28:01.085Z"
    },
    {
        "key": "c_user",
        "value": "61560916929379",
        "domain": "facebook.com",
        "path": "/",
        "hostOnly": true,
        "creation": "2025-07-20T08:28:01.085Z",
        "lastAccessed": "2025-07-20T08:28:01.085Z"
    },
    {
        "key": "xs",
        "value": "5%3ABCv-GacuTx5UrA%3A2%3A1753000068%3A-1%3A-1",
        "domain": "facebook.com",
        "path": "/",
        "hostOnly": true,
        "creation": "2025-07-20T08:28:01.085Z",
        "lastAccessed": "2025-07-20T08:28:01.085Z"
    },
    {
        "key": "fbl_st",
        "value": "101723228%3BT%3A29216667",
        "domain": "facebook.com",
        "path": "/",
        "hostOnly": true,
        "creation": "2025-07-20T08:28:01.085Z",
        "lastAccessed": "2025-07-20T08:28:01.085Z"
    },
    {
        "key": "dbln",
        "value": "%7B%2261560916929379%22%3A%22GWd3FGlS%22%7D",
        "domain": "facebook.com",
        "path": "/login/device-based/",
        "hostOnly": true,
        "creation": "2025-07-20T08:28:01.085Z",
        "lastAccessed": "2025-07-20T08:28:01.085Z"
    }
]
